ula.vhd
library ieee;
use ieee.std_logic_1164.all;
use ieee.numeric_std.all;

entity ula is
	port (
		entrada_a : in unsigned(15 downto 0);
		entrada_b : in unsigned(15 downto 0);
		selec_op : in unsigned(1 downto 0);
		
		saida : out unsigned(15 downto 0);
		
		flag_c : out std_logic; -- CarryOut -> relativo a BLS
		flag_z : out std_logic; -- Zero -> relativo a BLS
		flag_n : out std_logic -- Negativo -> relativo a BMI
	);
end entity;

architecture a_ula of ula is 

	signal soma, sub: unsigned(16 downto 0); -- um bitzinho a mais por causa do CarryOut
	signal s_and, s_or : unsigned(15 downto 0);
	signal saida_interna: unsigned(15 downto 0);
	
begin	
	
	-- soma subtração and or
	soma <= ('0' & entrada_a) + ('0' & entrada_b);
	sub <= ('0' & entrada_a) - ('0' & entrada_b);
	s_and <= entrada_a and entrada_b;
	s_or <= entrada_a or entrada_b;
	
	saida_interna <= soma(15 downto 0) when selec_op = "00" else
					 sub(15 downto 0) when selec_op = "01" else
					 s_and when selec_op = "10" else
					 s_or when selec_op = "11" else
					 x"0000";
	
	saida <= saida_interna;
	
	-- CarryOut
	flag_c <= soma(16) when selec_op = "00" else
			  sub(16) when selec_op = "01" else
			  '0';
	
	-- Zero
	flag_z <= '1' when saida_interna = x"0000" else '0';
	
	-- Negativo 
	flag_n <= saida_interna(15);
	
end architecture;

src/reg16bits.vhd
library ieee;
use ieee.std_logic_1164.all;
use ieee.numeric_std.all;

entity reg16bits is
	port(
		clk : in std_logic;
		rst : in std_logic;
		wr_en : in std_logic;
		data_in : in unsigned(15 downto 0);
		data_out : out unsigned(15 downto 0)
	);
end entity;

architecture a_reg16bits of reg16bits is
	signal registro: unsigned(15 downto 0);
begin
	process(clk, rst, wr_en)
	begin 
		if rst='1' then 
			registro <= x"0000";
		elsif wr_en='1' then 
			if rising_edge(clk) then
				registro <= data_in;
			end if;
		end if;
	end process;
	
	data_out <= registro;
end architecture;

src/banco_regs.vhd
library ieee;
use ieee.std_logic_1164.all;
use ieee.numeric_std.all;

entity banco_regs is
	port(
		clk : in std_logic;
		rst : in std_logic;
		wr_en : in std_logic;
		
		reg_sel_read : in unsigned(2 downto 0);
		reg_sel_write : in unsigned(2 downto 0);
		
		data_in : in unsigned(15 downto 0); -- do acumulador
		
		data_out : out unsigned(15 downto 0)
	);
end entity;

architecture a_banco_regs of banco_regs is 

	component reg16bits is
		port(
            clk      : in std_logic;
            rst      : in std_logic;
            wr_en    : in std_logic;
            data_in  : in unsigned(15 downto 0);
            data_out : out unsigned(15 downto 0)
        );
    end component;
	-- adicao de um 5 reg para cumprir com C D F
	signal r0_out, r1_out, r2_out, r3_out, r4_out, r5_out : unsigned(15 downto 0); -- sinal saida dos regs
	signal r0_en, r1_en, r2_en, r3_en, r4_en, r5_en : std_logic; -- enable dos regs
	
begin 
	
	r0_en <= '1' when (wr_en = '1' and reg_sel_write = "000") else '0';
	r1_en <= '1' when (wr_en = '1' and reg_sel_write = "001") else '0';
	r2_en <= '1' when (wr_en = '1' and reg_sel_write = "010") else '0';
	r3_en <= '1' when (wr_en = '1' and reg_sel_write = "011") else '0';
	r4_en <= '1' when (wr_en = '1' and reg_sel_write = "100") else '0';
	r5_en <= '1' when (wr_en = '1' and reg_sel_write = "101") else '0';
	
	-- instanciação
	r0: reg16bits port map(clk => clk, rst => rst, wr_en => r0_en, data_in => data_in, data_out => r0_out);
	r1: reg16bits port map(clk => clk, rst => rst, wr_en => r1_en, data_in => data_in, data_out => r1_out);
	r2: reg16bits port map(clk => clk, rst => rst, wr_en => r2_en, data_in => data_in, data_out => r2_out);
	r3: reg16bits port map(clk => clk, rst => rst, wr_en => r3_en, data_in => data_in, data_out => r3_out);
	r4: reg16bits port map(clk => clk, rst => rst, wr_en => r4_en, data_in => data_in, data_out => r4_out);
	r5: reg16bits port map(clk => clk, rst => rst, wr_en => r5_en, data_in => data_in, data_out => r5_out);
	
	data_out <= r0_out when reg_sel_read = "000" else
				r1_out when reg_sel_read = "001" else
				r2_out when reg_sel_read = "010" else
				r3_out when reg_sel_read = "011" else
				r4_out when reg_sel_read = "100" else
				r5_out when reg_sel_read = "101" else
				x"0000";

end architecture;

src/rom.vhd
library ieee;
use ieee.std_logic_1164.all;
use ieee.numeric_std.all;

entity rom is
    port(
        clk : in  std_logic;
        endereco : in  unsigned(6 downto 0);
        dado : out unsigned(18 downto 0)
    );
end entity;

architecture a_rom of rom is

    type mem is array (0 to 127) of unsigned(18 downto 0);

    constant conteudo_rom : mem := (
		0  => B"0001_000_000000000101", -- 00: LD 5
        1  => B"0011_001_000000000000", -- 01: MOV R1
        2  => B"0001_000_000000001000", -- 02: LD 8
        3  => B"0011_010_000000000000", -- 03: MOV R2

        4  => B"0001_000_000000000101", -- 04: LD 5
        5  => B"0101_010_000000000000", -- 05: SUB R2
        6  => B"1000_000_000000001100", -- 06: BLS 12 (Pula pra Linha 12)
        7  => B"0001_000_000000000001", -- 07: LD 1
        8  => B"0011_101_000000000000", -- 08: MOV R5
        9  => B"0001_000_000000000000", -- 09: LD 0
        10 => B"0101_001_000000000000", -- 10: SUB R1
        11 => B"1001_000_000000000111", -- 11: BMI 07 (Loop)

        12 => B"0001_000_000000000101", -- 12: LD 5
        13 => B"0101_010_000000000000", -- 13: SUB R2
        14 => B"1001_000_000000010100", -- 14: BMI 20 (Pula pra Linha 20)
        15 => B"0001_000_000000000010", -- 15: LD 2
        16 => B"0011_101_000000000000", -- 16: MOV R5
        17 => B"0001_000_000000000000", -- 17: LD 0
        18 => B"0101_001_000000000000", -- 18: SUB R1
        19 => B"1001_000_000000001111", -- 19: BMI 15 (Loop)

        20 => B"0001_000_000000000101", -- 20: LD 5
        21 => B"0101_001_000000000000", -- 21: SUB R1
        22 => B"1001_000_000000011001", -- 22: BMI 25 (Erro, vai pra 25)
        23 => B"1000_000_000000011110", -- 23: BLS 30 (Pula pra Linha 30)   
        24 => B"0000_000_000000000000", -- 24: NOP  
        25 => B"0001_000_000000000011", -- 25: LD 3
        26 => B"0011_101_000000000000", -- 26: MOV R5
        27 => B"0001_000_000000000000", -- 27: LD 0
        28 => B"0101_001_000000000000", -- 28: SUB R1
        29 => B"1001_000_000000011001", -- 29: BMI 25 (Loop)

        30 => B"0001_000_000000001000", -- 30: LD 8
        31 => B"0101_001_000000000000", -- 31: SUB R1
        32 => B"1000_000_000000100110", -- 32: BLS 38 (Erro, vai pra 38)
        33 => B"1001_000_000000100110", -- 33: BMI 38 (Erro, vai pra 38)
        34 => B"0001_000_000000000000", -- 34: LD 0
        35 => B"0101_001_000000000000", -- 35: SUB R1
        36 => B"1001_000_000000101011", -- 36: BMI 43 (Pula pro Sucesso Geral)
        37 => B"0000_000_000000000000", -- 37: NOP
        38 => B"0001_000_000000000100", -- 38: LD 4
        39 => B"0011_101_000000000000", -- 39: MOV R5
        40 => B"0001_000_000000000000", -- 40: LD 0
        41 => B"0101_001_000000000000", -- 41: SUB R1
        42 => B"1001_000_000000100110", -- 42: BMI 38 (Loop)

        43 => B"0001_000_000001100011", -- 43: LD 99 (1100011 em binário)
        44 => B"0011_101_000000000000", -- 44: MOV R5
        45 => B"0001_000_000000000000", -- 45: LD 0
        46 => B"0101_001_000000000000", -- 46: SUB R1
        47 => B"1001_000_000000101011", -- 47: BMI 43 (Trava executando com sucesso)

        others => (others => '0')          
    );

begin
	
	-- síncrona
    process(clk)
    begin
        if rising_edge(clk) then
            dado <= conteudo_rom(to_integer(endereco));
        end if;
    end process;

end architecture;

src/uc.vhd
library ieee;
use ieee.std_logic_1164.all;
use ieee.numeric_std.all;

entity uc is
    port(
        clk, rst          : in std_logic;
        pc_out            : out unsigned(6 downto 0);
        instr_out         : out unsigned(18 downto 0);
        estado_out        : out unsigned(1 downto 0);
        mux_acumulador    : out std_logic;
        wr_en_acumulador  : out std_logic;
        mux_ula_b         : out std_logic;
        selec_op_ula      : out unsigned(1 downto 0);
        wr_en_banco       : out std_logic
    );
end entity;

architecture a_uc of uc is
    component rom is
        port( clk : in std_logic; endereco : in unsigned(6 downto 0); dado : out unsigned(18 downto 0) );
    end component;

    -- Sinais da Máquina de Estados
    signal estado_s     : unsigned(1 downto 0);
    signal reg_pc       : unsigned(6 downto 0);
    signal next_pc       : unsigned(6 downto 0);
    signal pc_inc        : unsigned(6 downto 0);
    signal reg_instr    : unsigned(18 downto 0);
    signal proximo_reg_instr : unsigned(18 downto 0);
    signal sinal_dado   : unsigned(18 downto 0);
    signal sinal_opcode : unsigned(3 downto 0);

begin

    memoria: rom port map(clk => clk, endereco => reg_pc, dado => sinal_dado);

    -- maquina de 3 estados
    process(clk,rst)
    begin
        if rst='1' then
            estado_s <= "00";
        elsif rising_edge(clk) then
            if estado_s = "10" then        -- se agora esta em 2
                estado_s <= "00";         -- o prox vai voltar ao zero
            else
                estado_s <= estado_s + 1;   -- senao avanca
            end if;
        end if;
    end process;
    estado_out <= estado_s;

    -- Registrador de Instrução
    proximo_reg_instr <= sinal_dado when estado_s = "01" else reg_instr;

    process(clk)
    begin
        if rising_edge(clk) then
            reg_instr <= proximo_reg_instr;
        end if;
    end process;

    sinal_opcode <= reg_instr(18 downto 15);

    -- Decodificador
    mux_acumulador <= '1' when estado_s /= "10" else
                      '1' when sinal_opcode = "0001" else
                      '0' when sinal_opcode = "0100" or sinal_opcode = "0101" or sinal_opcode = "0110" else
                      '1';

    wr_en_acumulador <= '0' when estado_s /= "10" else
                        '1' when sinal_opcode = "0001" or sinal_opcode = "0100" or sinal_opcode = "0101" or sinal_opcode = "0110" else
                        '0';

    mux_ula_b <= '0' when estado_s /= "10" else
                  '1' when sinal_opcode = "0001" or sinal_opcode = "0110" else
                  '0';

    selec_op_ula <= "00" when estado_s /= "10" or sinal_opcode = "0001" or sinal_opcode = "0011" or sinal_opcode = "0100" or sinal_opcode = "0110" else
                     "01" when sinal_opcode = "0101" else
                     "00";

    wr_en_banco <= '0' when estado_s /= "10" else
                   '1' when sinal_opcode = "0011" else
                   '0';

    -- PC
    pc_inc <= reg_pc + 1;
    next_pc <= reg_instr(6 downto 0) when (estado_s = "10" and sinal_opcode = "0111") else
               pc_inc when (estado_s = "10") else
               reg_pc; 

    process(clk, rst)
    begin
        if rst = '1' then 
            reg_pc <= (others => '0');
        elsif rising_edge(clk) then
            reg_pc <= next_pc;
        end if;
    end process;

    pc_out <= reg_pc;
    instr_out <= reg_instr;
    estado_out <= estado_s;

end architecture;

src/processador.vhd
library ieee;
use ieee.std_logic_1164.all;
use ieee.numeric_std.all;

entity processador is 
    port(
        clk, rst : in std_logic;
        constante_externa : in unsigned(15 downto 0);
        saida : out unsigned(15 downto 0);
        flag_z, flag_n, flag_c : out std_logic 
    );
end entity;

architecture a_processador of processador is 

    component uc is
        port(
            clk, rst : in std_logic;
            pc_out : out unsigned(6 downto 0);
            instr_out : out unsigned(18 downto 0);
            estado_out : out unsigned(1 downto 0);
            mux_acumulador : out std_logic;
			 wr_en_acumulador : out std_logic;
            mux_ula_b : out std_logic;
            selec_op_ula : out unsigned(1 downto 0);
            wr_en_banco : out std_logic
        );
    end component;

    component ula is
        port(
            entrada_a, entrada_b : in unsigned(15 downto 0);
            selec_op : in unsigned(1 downto 0);
            saida : out unsigned(15 downto 0);
            flag_c, flag_z, flag_n : out std_logic
        );
    end component;

    component banco_regs is
        port(
            clk, rst : in std_logic;
            wr_en : in std_logic;
            reg_sel_read, reg_sel_write : in unsigned(2 downto 0);
            data_in : in unsigned(15 downto 0);
            data_out : out unsigned(15 downto 0)
        );
    end component;

    component reg16bits is 
        port (
            clk, rst : in std_logic;
            wr_en : in std_logic;
            data_in : in unsigned(15 downto 0);
            data_out : out unsigned(15 downto 0)
        );
    end component;

    -- sinais
    signal s_mux_acc, s_wr_acc, s_mux_ula, s_wr_banco : std_logic;
    signal s_sel_op_ula : unsigned(1 downto 0);
    signal s_instr : unsigned(18 downto 0);
    signal saida_ula, saida_acumulador, saida_banco : unsigned(15 downto 0);
    signal sinal_mux_ula_b, sinal_mux_acumulador : unsigned(15 downto 0);
	signal s_constante_interna : unsigned(15 downto 0);

begin 
    -- pega os 12 MSB da instrução e ajusta p/16 com sinal
	s_constante_interna <= unsigned(resize(signed(s_instr(11 downto 0)), 16));

    -- fiação
    controle : uc port map(
        clk => clk, rst => rst,
        instr_out => s_instr,
        mux_acumulador => s_mux_acc, wr_en_acumulador => s_wr_acc,
        mux_ula_b => s_mux_ula, selec_op_ula => s_sel_op_ula,
        wr_en_banco => s_wr_banco
    );

	sinal_mux_ula_b <= saida_banco when s_mux_ula = '0' else s_constante_interna;
	sinal_mux_acumulador <= saida_ula when s_mux_acc = '0' else s_constante_interna;

    acumulador_ula : reg16bits port map(clk, rst, s_wr_acc, sinal_mux_acumulador, saida_acumulador);
    
    banco : banco_regs port map(
        clk, rst, s_wr_banco, 
        s_instr(14 downto 12), s_instr(14 downto 12), 
        saida_acumulador, saida_banco
    );

    ula_processador : ula port map(saida_acumulador, sinal_mux_ula_b, s_sel_op_ula, saida_ula, flag_c, flag_z, flag_n);
    
    saida <= saida_acumulador;

end architecture;

src/processador_tb.vhd
library ieee;
use ieee.std_logic_1164.all;
use ieee.numeric_std.all;

entity processador_tb is
end entity;

architecture a_processador_tb of processador_tb is
    component processador is 
        port(
            clk, rst : in std_logic;
            constante_externa : in unsigned(15 downto 0);
            saida : out unsigned(15 downto 0);
            flag_z, flag_n, flag_c : out std_logic 
        );
    end component;

    -- sinais
    signal clk, rst : std_logic := '0';
    signal constante_externa : unsigned(15 downto 0) := (others => '0');
    signal monitor : unsigned(15 downto 0);
    signal fz, fn, fc : std_logic;
    signal finished : std_logic := '0';

begin

    uut: processador port map (
        clk => clk, 
        rst => rst, 
        constante_externa => constante_externa,
        saida => monitor,
        flag_z => fz, 
        flag_n => fn, 
        flag_c => fc
    );

    -- clk; T = 100ns
    clk_proc: process
    begin
        while finished /= '1' loop
            clk <= '0'; wait for 50 ns;
            clk <= '1'; wait for 50 ns;
        end loop;
        wait;
    end process;

    stim_proc: process
    begin
        rst <= '1';
        wait for 200 ns;
        rst <= '0';
        
        wait for 110000 ns; 

        finished <= '1';
        wait;
    end process;
end architecture;

sim.vcd
$date
  Fri May 22 10:14:06 2026
$end
$version
  GHDL v0
$end
$timescale
  1 fs
$end
$scope module standard $end
$upscope $end
$scope module std_logic_1164 $end
$upscope $end
$scope module numeric_std $end
$upscope $end
$scope module processador_tb $end
$var reg 1 ! clk $end
$var reg 1 " rst $end
$var reg 16 # constante_externa[15:0] $end
$var reg 16 $ monitor[15:0] $end
$var reg 1 % fz $end
$var reg 1 & fn $end
$var reg 1 ' fc $end
$var reg 1 ( finished $end
$scope module uut $end
$var reg 1 ) clk $end
$var reg 1 * rst $end
$var reg 16 + constante_externa[15:0] $end
$var reg 16 , saida[15:0] $end
$var reg 1 - flag_z $end
$var reg 1 . flag_n $end
$var reg 1 / flag_c $end
$var reg 1 0 s_mux_acc $end
$var reg 1 1 s_wr_acc $end
$var reg 1 2 s_mux_ula $end
$var reg 1 3 s_wr_banco $end
$var reg 2 4 s_sel_op_ula[1:0] $end
$var reg 19 5 s_instr[18:0] $end
$var reg 16 6 saida_ula[15:0] $end
$var reg 16 7 saida_acumulador[15:0] $end
$var reg 16 8 saida_banco[15:0] $end
$var reg 16 9 sinal_mux_ula_b[15:0] $end
$var reg 16 : sinal_mux_acumulador[15:0] $end
$var reg 16 ; s_constante_interna[15:0] $end
$scope module controle $end
$var reg 1 < clk $end
$var reg 1 = rst $end
$var reg 7 > pc_out[6:0] $end
$var reg 19 ? instr_out[18:0] $end
$var reg 2 @ estado_out[1:0] $end
$var reg 1 A mux_acumulador $end
$var reg 1 B wr_en_acumulador $end
$var reg 1 C mux_ula_b $end
$var reg 2 D selec_op_ula[1:0] $end
$var reg 1 E wr_en_banco $end
$var reg 2 F estado_s[1:0] $end
$var reg 7 G reg_pc[6:0] $end
$var reg 7 H next_pc[6:0] $end
$var reg 7 I pc_inc[6:0] $end
$var reg 19 J reg_instr[18:0] $end
$var reg 19 K proximo_reg_instr[18:0] $end
$var reg 19 L sinal_dado[18:0] $end
$var reg 4 M sinal_opcode[3:0] $end
$scope module memoria $end
$var reg 1 N clk $end
$var reg 7 O endereco[6:0] $end
$var reg 19 P dado[18:0] $end
$upscope $end
$upscope $end
$scope module acumulador_ula $end
$var reg 1 Q clk $end
$var reg 1 R rst $end
$var reg 1 S wr_en $end
$var reg 16 T data_in[15:0] $end
$var reg 16 U data_out[15:0] $end
$var reg 16 V registro[15:0] $end
$upscope $end
$scope module banco $end
$var reg 1 W clk $end
$var reg 1 X rst $end
$var reg 1 Y wr_en $end
$var reg 3 Z reg_sel_read[2:0] $end
$var reg 3 [ reg_sel_write[2:0] $end
$var reg 16 \ data_in[15:0] $end
$var reg 16 ] data_out[15:0] $end
$var reg 16 ^ r0_out[15:0] $end
$var reg 16 _ r1_out[15:0] $end
$var reg 16 ` r2_out[15:0] $end
$var reg 16 a r3_out[15:0] $end
$var reg 16 b r4_out[15:0] $end
$var reg 16 c r5_out[15:0] $end
$var reg 1 d r0_en $end
$var reg 1 e r1_en $end
$var reg 1 f r2_en $end
$var reg 1 g r3_en $end
$var reg 1 h r4_en $end
$var reg 1 i r5_en $end
$scope module r0 $end
$var reg 1 j clk $end
$var reg 1 k rst $end
$var reg 1 l wr_en $end
$var reg 16 m data_in[15:0] $end
$var reg 16 n data_out[15:0] $end
$var reg 16 o registro[15:0] $end
$upscope $end
$scope module r1 $end
$var reg 1 p clk $end
$var reg 1 q rst $end
$var reg 1 r wr_en $end
$var reg 16 s data_in[15:0] $end
$var reg 16 t data_out[15:0] $end
$var reg 16 u registro[15:0] $end
$upscope $end
$scope module r2 $end
$var reg 1 v clk $end
$var reg 1 w rst $end
$var reg 1 x wr_en $end
$var reg 16 y data_in[15:0] $end
$var reg 16 z data_out[15:0] $end
$var reg 16 { registro[15:0] $end
$upscope $end
$scope module r3 $end
$var reg 1 | clk $end
$var reg 1 } rst $end
$var reg 1 !" wr_en $end
$var reg 16 "" data_in[15:0] $end
$var reg 16 #" data_out[15:0] $end
$var reg 16 $" registro[15:0] $end
$upscope $end
$scope module r4 $end
$var reg 1 %" clk $end
$var reg 1 &" rst $end
$var reg 1 '" wr_en $end
$var reg 16 (" data_in[15:0] $end
$var reg 16 )" data_out[15:0] $end
$var reg 16 *" registro[15:0] $end
$upscope $end
$scope module r5 $end
$var reg 1 +" clk $end
$var reg 1 ," rst $end
$var reg 1 -" wr_en $end
$var reg 16 ." data_in[15:0] $end
$var reg 16 /" data_out[15:0] $end
$var reg 16 0" registro[15:0] $end
$upscope $end
$upscope $end
$scope module ula_processador $end
$var reg 16 1" entrada_a[15:0] $end
$var reg 16 2" entrada_b[15:0] $end
$var reg 2 3" selec_op[1:0] $end
$var reg 16 4" saida[15:0] $end
$var reg 1 5" flag_c $end
$var reg 1 6" flag_z $end
$var reg 1 7" flag_n $end
$var reg 17 8" soma[16:0] $end
$var reg 17 9" sub[16:0] $end
$var reg 16 :" s_and[15:0] $end
$var reg 16 ;" s_or[15:0] $end
$var reg 16 <" saida_interna[15:0] $end
$upscope $end
$upscope $end
$upscope $end
$enddefinitions $end
#0
0!
1"
b0000000000000000 #
b0000000000000000 $
1%
0&
0'
0(
0)
1*
b0000000000000000 +
b0000000000000000 ,
1-
0.
0/
10
01
02
03
b00 4
bUUUUUUUUUUUUUUUUUUU 5
b0000000000000000 6
b0000000000000000 7
b0000000000000000 8
b0000000000000000 9
bUUUUUUUUUUUUUUUU :
bUUUUUUUUUUUUUUUU ;
0<
1=
b0000000 >
bUUUUUUUUUUUUUUUUUUU ?
b00 @
1A
0B
0C
b00 D
0E
b00 F
b0000000 G
b0000000 H
b0000001 I
bUUUUUUUUUUUUUUUUUUU J
bUUUUUUUUUUUUUUUUUUU K
bUUUUUUUUUUUUUUUUUUU L
bUUUU M
0N
b0000000 O
bUUUUUUUUUUUUUUUUUUU P
0Q
1R
0S
bUUUUUUUUUUUUUUUU T
b0000000000000000 U
b0000000000000000 V
0W
1X
0Y
bUUU Z
bUUU [
b0000000000000000 \
b0000000000000000 ]
b0000000000000000 ^
b0000000000000000 _
b0000000000000000 `
b0000000000000000 a
b0000000000000000 b
b0000000000000000 c
0d
0e
0f
0g
0h
0i
0j
1k
0l
b0000000000000000 m
b0000000000000000 n
b0000000000000000 o
0p
1q
0r
b0000000000000000 s
b0000000000000000 t
b0000000000000000 u
0v
1w
0x
b0000000000000000 y
b0000000000000000 z
b0000000000000000 {
0|
1}
0!"
b0000000000000000 ""
b0000000000000000 #"
b0000000000000000 $"
0%"
1&"
0'"
b0000000000000000 ("
b0000000000000000 )"
b0000000000000000 *"
0+"
1,"
0-"
b0000000000000000 ."
b0000000000000000 /"
b0000000000000000 0"
b0000000000000000 1"
b0000000000000000 2"
b00 3"
b0000000000000000 4"
05"
16"
07"
b00000000000000000 8"
b00000000000000000 9"
b0000000000000000 :"
b0000000000000000 ;"
b0000000000000000 <"
#50000000
1!
1)
1<
b0001000000000000101 L
1N
b0001000000000000101 P
1Q
1W
1j
1p
1v
1|
1%"
1+"
#100000000
0!
0)
0<
0N
0Q
0W
0j
0p
0v
0|
0%"
0+"
#150000000
1!
1)
1<
1N
1Q
1W
1j
1p
1v
1|
1%"
1+"
#200000000
0!
0"
0)
0*
0<
0=
0N
0Q
0R
0W
0X
0j
0k
0p
0q
0v
0w
0|
0}
0%"
0&"
0+"
0,"
#250000000
1!
1)
1<
b01 @
b01 F
b0001000000000000101 K
1N
1Q
1W
1j
1p
1v
1|
1%"
1+"
#300000000
0!
0)
0<
0N
0Q
0W
0j
0p
0v
0|
0%"
0+"
#350000000
1!
0%
1)
0-
11
12
b0001000000000000101 5
b0000000000000101 6
b0000000000000101 9
b0000000000000101 :
b0000000000000101 ;
1<
b0001000000000000101 ?
b10 @
1B
1C
b10 F
b0000001 H
b0001000000000000101 J
b0001 M
1N
1Q
1S
b0000000000000101 T
1W
b000 Z
b000 [
1j
1p
1v
1|
1%"
1+"
b0000000000000101 2"
b0000000000000101 4"
06"
b00000000000000101 8"
b00000000000000101 9"
b0000000000000101 ;"
b0000000000000101 <"
#400000000
0!
0)
0<
0N
0Q
0W
0j
0p
0v
0|
0%"
0+"
#450000000
1!
b0000000000000101 $
1)
b0000000000000101 ,
01
02
b0000000000000101 6
b0000000000000101 7
b0000000000000000 9
1<
b0000001 >
b00 @
0B
0C
b00 F
b0000001 G
b0000010 I
1N
b0000001 O
1Q
0S
b0000000000000101 U
b0000000000000101 V
1W
b0000000000000101 \
1j
b0000000000000101 m
1p
b0000000000000101 s
1v
b0000000000000101 y
1|
b0000000000000101 ""
1%"
b0000000000000101 ("
1+"
b0000000000000101 ."
b0000000000000101 1"
b0000000000000000 2"
b0000000000000101 4"
b00000000000000101 8"
b11111111111111011 9"
b0000000000000000 :"
b0000000000000101 <"
#500000000
0!
0)
0<
0N
0Q
0W
0j
0p
0v
0|
0%"
0+"
#550000000
1!
1)
1<
b01 @
b01 F
b0011011000000000000 K
b0011011000000000000 L
1N
b0011011000000000000 P
1Q
1W
1j
1p
1v
1|
1%"
1+"
#600000000
0!
0)
0<
0N
0Q
0W
0j
0p
0v
0|
0%"
0+"
#650000000
1!
1)
01
02
13
b0011011000000000000 5
b0000000000000101 6
b0000000000000000 9
b0000000000000000 :
b0000000000000000 ;
1<
b0011011000000000000 ?
b10 @
0B
0C
1E
b10 F
b0000010 H
b0011011000000000000 J
b0011 M
1N
1Q
0S
b0000000000000000 T
1W
1Y
b011 Z
b011 [
1g
1j
1p
1v
1|
1!"
1%"
1+"
b0000000000000000 2"
b0000000000000101 4"
b00000000000000101 8"
b11111111111111011 9"
b0000000000000000 :"
b0000000000000101 <"
#700000000
0!
0)
0<
0N
0Q
0W
0j
0p
0v
0|
0%"
0+"
#750000000
1!
1)
03
b0000000000001010 6
b0000000000000101 8
b0000000000000101 9
1<
b0000010 >
b00 @
0E
b00 F
b0000010 G
b0000011 I
1N
b0000010 O
1Q
1W
0Y
b0000000000000101 ]
b0000000000000101 a
0g
1j
1p
1v
1|
0!"
b0000000000000101 #"
b0000000000000101 $"
1%"
1+"
b0000000000000101 2"
b0000000000001010 4"
b00000000000001010 8"
b00000000000000000 9"
b0000000000000101 :"
b0000000000001010 <"
#800000000
0!
0)
0<
0N
0Q
0W
0j
0p
0v
0|
0%"
0+"
#850000000
1!
1)
1<
b01 @
b01 F
b0001000000000001000 K
b0001000000000001000 L
1N
b0001000000000001000 P
1Q
1W
1j
1p
1v
1|
1%"
1+"
#900000000
0!
0)
0<
0N
0Q
0W
0j
0p
0v
0|
0%"
0+"
#950000000
1!
1)
11
12
03
b0001000000000001000 5
b0000000000001101 6
b0000000000000000 8
b0000000000001000 9
b0000000000001000 :
b0000000000001000 ;
1<
b0001000000000001000 ?
b10 @
1B
1C
0E
b10 F
b0000011 H
b0001000000000001000 J
b0001 M
1N
1Q
1S
b0000000000001000 T
1W
0Y
b000 Z
b000 [
b0000000000000000 ]
0d
1j
0l
1p
1v
1|
1%"
1+"
b0000000000001000 2"
b0000000000001101 4"
b00000000000001101 8"
b00000000000000011 9"
b0000000000000000 :"
b0000000000001101 ;"
b0000000000001101 <"
#1000000000
0!
0)
0<
0N
0Q
0W
0j
0p
0v
0|
0%"
0+"
#1050000000
1!
b0000000000001000 $
1)
b0000000000001000 ,
01
02
b0000000000001000 6
b0000000000001000 7
b0000000000000000 9
1<
b0000011 >
b00 @
0B
0C
b00 F
b0000011 G
b0000100 I
1N
b0000011 O
1Q
0S
b0000000000001000 U
b0000000000001000 V
1W
b0000000000001000 \
1j
b0000000000001000 m
1p
b0000000000001000 s
1v
b0000000000001000 y
1|
b0000000000001000 ""
1%"
b0000000000001000 ("
1+"
b0000000000001000 ."
b0000000000001000 1"
b0000000000000000 2"
b0000000000001000 4"
b00000000000001000 8"
b11111111111111000 9"
b0000000000000000 :"
b0000000000001000 ;"
b0000000000001000 <"
#1100000000
0!
0)
0<
0N
0Q
0W
0j
0p
0v
0|
0%"
0+"
#1150000000
1!
1)
1<
b01 @
b01 F
b0011100000000000000 K
b0011100000000000000 L
1N
b0011100000000000000 P
1Q
1W
1j
1p
1v
1|
1%"
1+"
#1200000000
0!
0)
0<
0N
0Q
0W
0j
0p
0v
0|
0%"
0+"
#1250000000
1!
1)
01
02
13
b0011100000000000000 5
b0000000000001000 6
b0000000000000000 9
b0000000000000000 :
b0000000000000000 ;
1<
b0011100000000000000 ?
b10 @
0B
0C
1E
b10 F
b0000100 H
b0011100000000000000 J
b0011 M
1N
1Q
0S
b0000000000000000 T
1W
1Y
b100 Z
b100 [
1h
1j
1p
1v
1|
1%"
1'"
1+"
b0000000000000000 2"
b0000000000001000 4"
b00000000000001000 8"
b11111111111111000 9"
b0000000000000000 :"
b0000000000001000 <"
#1300000000
0!
0)
0<
0N
0Q
0W
0j
0p
0v
0|
0%"
0+"
#1350000000
1!
1)
03
b0000000000010000 6
b0000000000001000 8
b0000000000001000 9
1<
b0000100 >
b00 @
0E
b00 F
b0000100 G
b0000101 I
1N
b0000100 O
1Q
1W
0Y
b0000000000001000 ]
b0000000000001000 b
0h
1j
1p
1v
1|
1%"
0'"
b0000000000001000 )"
b0000000000001000 *"
1+"
b0000000000001000 2"
b0000000000010000 4"
b00000000000010000 8"
b00000000000000000 9"
b0000000000001000 :"
b0000000000010000 <"
#1400000000
0!
0)
0<
0N
0Q
0W
0j
0p
0v
0|
0%"
0+"
#1450000000
1!
1)
1<
b01 @
b01 F
b0001000000000000000 K
b0001000000000000000 L
1N
b0001000000000000000 P
1Q
1W
1j
1p
1v
1|
1%"
1+"
#1500000000
0!
0)
0<
0N
0Q
0W
0j
0p
0v
0|
0%"
0+"
#1550000000
1!
1)
11
12
03
b0001000000000000000 5
b0000000000001000 6
b0000000000000000 8
b0000000000000000 9
1<
b0001000000000000000 ?
b10 @
1B
1C
0E
b10 F
b0000101 H
b0001000000000000000 J
b0001 M
1N
1Q
1S
1W
0Y
b000 Z
b000 [
b0000000000000000 ]
0d
1j
0l
1p
1v
1|
1%"
1+"
b0000000000000000 2"
b0000000000001000 4"
b00000000000001000 8"
b11111111111111000 9"
b0000000000000000 :"
b0000000000001000 <"
#1600000000
0!
0)
0<
0N
0Q
0W
0j
0p
0v
0|
0%"
0+"
#1650000000
1!
b0000000000000000 $
1%
1)
b0000000000000000 ,
1-
01
02
b0000000000000000 6
b0000000000000000 7
1<
b0000101 >
b00 @
0B
0C
b00 F
b0000101 G
b0000110 I
1N
b0000101 O
1Q
0S
b0000000000000000 U
b0000000000000000 V
1W
b0000000000000000 \
1j
b0000000000000000 m
1p
b0000000000000000 s
1v
b0000000000000000 y
1|
b0000000000000000 ""
1%"
b0000000000000000 ("
1+"
b0000000000000000 ."
b0000000000000000 1"
b0000000000000000 4"
16"
b00000000000000000 8"
b00000000000000000 9"
b0000000000000000 ;"
b0000000000000000 <"
#1700000000
0!
0)
0<
0N
0Q
0W
0j
0p
0v
0|
0%"
0+"
#1750000000
1!
1)
1<
b01 @
b01 F
b0100100000000000000 K
b0100100000000000000 L
1N
b0100100000000000000 P
1Q
1W
1j
1p
1v
1|
1%"
1+"
#1800000000
0!
0)
0<
0N
0Q
0W
0j
0p
0v
0|
0%"
0+"
